yassine_ramla_linear_regression
