Metadata-Version: 2.1
Name: yassine-ramla-linear-regression
Version: 1.0.1
Summary: An awesome package for linear regression
Home-page: http://pypi.python.org/pypi/yassine_ramla_linear_regression/
Author: yassine ramla
Author-email: y.ramla@esi-sba.dz
License: LICENSE.txt
Platform: UNKNOWN
License-File: LICENSE.txt
